mseep_ntropy_mcp-0.1.4.dist-info/licenses/LICENSE
ntropy_mcp/__init__.py
ntropy_mcp/server.py
mseep_ntropy_mcp-0.1.4.dist-info/METADATA
mseep_ntropy_mcp-0.1.4.dist-info/WHEEL
mseep_ntropy_mcp-0.1.4.dist-info/entry_points.txt
mseep_ntropy_mcp-0.1.4.dist-info/top_level.txt
mseep_ntropy_mcp-0.1.4.dist-info/RECORD
