Metadata-Version: 2.4
Name: mseep-ntropy-mcp
Version: 0.1.4
Summary: MCP server for enriching banking data using the Ntropy API
Author-email: mseep <support@skydeck.ai>
Requires-Python: >=3.10
License-File: LICENSE
Requires-Dist: mcp>=1.3.0
Requires-Dist: requests
Dynamic: license-file
